setup.py
smsified/__init__.py
smsified/api.py
smsified.egg-info/PKG-INFO
smsified.egg-info/SOURCES.txt
smsified.egg-info/dependency_links.txt
smsified.egg-info/requires.txt
smsified.egg-info/top_level.txt